README.rst
setup.cfg
setup.py
cacpy/CACPy.py
cacpy/__init__.py
cacpy.egg-info/PKG-INFO
cacpy.egg-info/SOURCES.txt
cacpy.egg-info/dependency_links.txt
cacpy.egg-info/requires.txt
cacpy.egg-info/top_level.txt