Metadata-Version: 1.1
Name: cacpy
Version: 0.5.2
Summary: A python wrapper for the cloudatcost.com API - https://github.com/cloudatcost/api
Home-page: https://github.com/adc4392/python-cloudatcost
Author: Andy Culler
Author-email: adc4392@gmail.com
License: MIT
Download-URL: https://github.com/adc4392/python-cloudatcost/tarball/0.5.2
Keywords: wrapper for cloud at cost api
Platform: UNKNOWN
Classifier: Intended Audience :: Developers
Classifier: Topic :: Software Development :: Libraries :: Python Modules
Classifier: Programming Language :: Python :: 2.7
Classifier: License :: OSI Approved :: MIT License
